{
"meta":{"test_sets":[],"test_metrics":[],"learn_metrics":[{"best_value":"Min","name":"RMSE"}],"launch_mode":"Train","parameters":"","iteration_count":100,"learn_sets":["learn"],"name":"experiment"},
"iterations":[
{"learn":[14.005006],"iteration":0,"passed_time":0.0009457840008,"remaining_time":0.09363261608},
{"learn":[13.14441192],"iteration":1,"passed_time":0.001725245032,"remaining_time":0.08453700655},
{"learn":[12.34258257],"iteration":2,"passed_time":0.002480179039,"remaining_time":0.08019245559},
{"learn":[11.64527793],"iteration":3,"passed_time":0.003047510651,"remaining_time":0.07314025561},
{"learn":[11.02766183],"iteration":4,"passed_time":0.003815324754,"remaining_time":0.07249117032},
{"learn":[10.43485794],"iteration":5,"passed_time":0.004617587139,"remaining_time":0.07234219851},
{"learn":[9.890641275],"iteration":6,"passed_time":0.00537615095,"remaining_time":0.07142600547},
{"learn":[9.492161212],"iteration":7,"passed_time":0.006209018881,"remaining_time":0.07140371714},
{"learn":[9.105082953],"iteration":8,"passed_time":0.00690007325,"remaining_time":0.06976740731},
{"learn":[8.674157135],"iteration":9,"passed_time":0.007671485753,"remaining_time":0.06904337178},
{"learn":[8.341743544],"iteration":10,"passed_time":0.008440725276,"remaining_time":0.06829314087},
{"learn":[8.049372916],"iteration":11,"passed_time":0.009297311396,"remaining_time":0.06818028357},
{"learn":[7.757318612],"iteration":12,"passed_time":0.01013796284,"remaining_time":0.0678463667},
{"learn":[7.522206899],"iteration":13,"passed_time":0.01099971793,"remaining_time":0.06756969583},
{"learn":[7.297756655],"iteration":14,"passed_time":0.01183379375,"remaining_time":0.06705816458},
{"learn":[7.088359431],"iteration":15,"passed_time":0.01260502855,"remaining_time":0.0661763999},
{"learn":[6.882113791],"iteration":16,"passed_time":0.01336371032,"remaining_time":0.06524635038},
{"learn":[6.704728832],"iteration":17,"passed_time":0.01421741726,"remaining_time":0.06476823418},
{"learn":[6.563881962],"iteration":18,"passed_time":0.01498512566,"remaining_time":0.06388395677},
{"learn":[6.418790279],"iteration":19,"passed_time":0.01577227829,"remaining_time":0.06308911317},
{"learn":[6.315756953],"iteration":20,"passed_time":0.01660329915,"remaining_time":0.06246003014},
{"learn":[6.210157751],"iteration":21,"passed_time":0.01750156559,"remaining_time":0.06205100526},
{"learn":[6.115058449],"iteration":22,"passed_time":0.01844991894,"remaining_time":0.06176711994},
{"learn":[6.014819884],"iteration":23,"passed_time":0.01929082583,"remaining_time":0.06108761513},
{"learn":[5.93117229],"iteration":24,"passed_time":0.02012584989,"remaining_time":0.06037754967},
{"learn":[5.844857622],"iteration":25,"passed_time":0.02096644542,"remaining_time":0.05967372927},
{"learn":[5.771145213],"iteration":26,"passed_time":0.02178195019,"remaining_time":0.05889193941},
{"learn":[5.704018229],"iteration":27,"passed_time":0.02257577955,"remaining_time":0.05805200455},
{"learn":[5.665806474],"iteration":28,"passed_time":0.02336617518,"remaining_time":0.05720684268},
{"learn":[5.616500369],"iteration":29,"passed_time":0.02420985593,"remaining_time":0.05648966383},
{"learn":[5.558023666],"iteration":30,"passed_time":0.02504958671,"remaining_time":0.0557555317},
{"learn":[5.510080976],"iteration":31,"passed_time":0.02593826851,"remaining_time":0.05511882059},
{"learn":[5.468747792],"iteration":32,"passed_time":0.02680856271,"remaining_time":0.05442950612},
{"learn":[5.429275534],"iteration":33,"passed_time":0.02755460949,"remaining_time":0.05348835959},
{"learn":[5.402117324],"iteration":34,"passed_time":0.028602383,"remaining_time":0.05311871128},
{"learn":[5.367635151],"iteration":35,"passed_time":0.02968681607,"remaining_time":0.0527765619},
{"learn":[5.345181232],"iteration":36,"passed_time":0.03070220475,"remaining_time":0.052276727},
{"learn":[5.319151269],"iteration":37,"passed_time":0.03157338744,"remaining_time":0.05151447425},
{"learn":[5.296134146],"iteration":38,"passed_time":0.03237336655,"remaining_time":0.05063526563},
{"learn":[5.269629003],"iteration":39,"passed_time":0.03320914966,"remaining_time":0.04981372449},
{"learn":[5.251147059],"iteration":40,"passed_time":0.03403575295,"remaining_time":0.04897827863},
{"learn":[5.248003302],"iteration":41,"passed_time":0.03431294768,"remaining_time":0.0473845468},
{"learn":[5.232376509],"iteration":42,"passed_time":0.03510483614,"remaining_time":0.04653431767},
{"learn":[5.213524255],"iteration":43,"passed_time":0.03589239472,"remaining_time":0.04568122964},
{"learn":[5.189691584],"iteration":44,"passed_time":0.03672665896,"remaining_time":0.04488813873},
{"learn":[5.166052198],"iteration":45,"passed_time":0.03752530456,"remaining_time":0.04405144449},
{"learn":[5.140406659],"iteration":46,"passed_time":0.03837886674,"remaining_time":0.04327829654},
{"learn":[5.118929684],"iteration":47,"passed_time":0.03916044484,"remaining_time":0.04242381524},
{"learn":[5.108792602],"iteration":48,"passed_time":0.03997253657,"remaining_time":0.04160406867},
{"learn":[5.098141225],"iteration":49,"passed_time":0.04075402965,"remaining_time":0.04075402965},
{"learn":[5.085926393],"iteration":50,"passed_time":0.04153448257,"remaining_time":0.03990567934},
{"learn":[5.067816804],"iteration":51,"passed_time":0.04238458958,"remaining_time":0.03912423654},
{"learn":[5.049834901],"iteration":52,"passed_time":0.04322729375,"remaining_time":0.03833363786},
{"learn":[5.03838627],"iteration":53,"passed_time":0.04399633183,"remaining_time":0.03747835675},
{"learn":[5.033534248],"iteration":54,"passed_time":0.04450880891,"remaining_time":0.0364162982},
{"learn":[5.023726885],"iteration":55,"passed_time":0.04543882291,"remaining_time":0.03570193229},
{"learn":[5.01290392],"iteration":56,"passed_time":0.0463696672,"remaining_time":0.03498062613},
{"learn":[5.005569127],"iteration":57,"passed_time":0.04717605802,"remaining_time":0.03416197305},
{"learn":[4.989969032],"iteration":58,"passed_time":0.04803875713,"remaining_time":0.03338286512},
{"learn":[4.976762446],"iteration":59,"passed_time":0.04893370396,"remaining_time":0.03262246931},
{"learn":[4.967222715],"iteration":60,"passed_time":0.04973458612,"remaining_time":0.03179752227},
{"learn":[4.954407599],"iteration":61,"passed_time":0.05063540391,"remaining_time":0.0310346024},
{"learn":[4.942125056],"iteration":62,"passed_time":0.05148650435,"remaining_time":0.03023810573},
{"learn":[4.930230716],"iteration":63,"passed_time":0.05230194631,"remaining_time":0.0294198448},
{"learn":[4.921695642],"iteration":64,"passed_time":0.05314656458,"remaining_time":0.02861738093},
{"learn":[4.906405625],"iteration":65,"passed_time":0.05400471475,"remaining_time":0.02782061063},
{"learn":[4.894330248],"iteration":66,"passed_time":0.05485690129,"remaining_time":0.02701907079},
{"learn":[4.88211557],"iteration":67,"passed_time":0.05571333499,"remaining_time":0.02621804},
{"learn":[4.877946398],"iteration":68,"passed_time":0.056637596,"remaining_time":0.02544587646},
{"learn":[4.863182126],"iteration":69,"passed_time":0.05751813621,"remaining_time":0.02465062981},
{"learn":[4.84646533],"iteration":70,"passed_time":0.0583490824,"remaining_time":0.0238327238},
{"learn":[4.838014752],"iteration":71,"passed_time":0.05917565657,"remaining_time":0.02301275533},
{"learn":[4.82981137],"iteration":72,"passed_time":0.06002333554,"remaining_time":0.02220041178},
{"learn":[4.817094767],"iteration":73,"passed_time":0.06085661785,"remaining_time":0.02138205492},
{"learn":[4.808314151],"iteration":74,"passed_time":0.06170987672,"remaining_time":0.02056995891},
{"learn":[4.796235023],"iteration":75,"passed_time":0.06254069422,"remaining_time":0.01974969291},
{"learn":[4.784434534],"iteration":76,"passed_time":0.06341600381,"remaining_time":0.0189424427},
{"learn":[4.774402487],"iteration":77,"passed_time":0.06424374222,"remaining_time":0.01812002986},
{"learn":[4.76731896],"iteration":78,"passed_time":0.06506550858,"remaining_time":0.01729589469},
{"learn":[4.75934113],"iteration":79,"passed_time":0.06590291166,"remaining_time":0.01647572791},
{"learn":[4.754106378],"iteration":80,"passed_time":0.06675511505,"remaining_time":0.01565860723},
{"learn":[4.744002932],"iteration":81,"passed_time":0.06757020851,"remaining_time":0.0148324848},
{"learn":[4.731700554],"iteration":82,"passed_time":0.06843465474,"remaining_time":0.01401673651},
{"learn":[4.723284153],"iteration":83,"passed_time":0.0692131729,"remaining_time":0.0131834615},
{"learn":[4.712232782],"iteration":84,"passed_time":0.07002472234,"remaining_time":0.01235730394},
{"learn":[4.703046867],"iteration":85,"passed_time":0.07089848166,"remaining_time":0.01154161329},
{"learn":[4.698601855],"iteration":86,"passed_time":0.0718034501,"remaining_time":0.01072925116},
{"learn":[4.692429407],"iteration":87,"passed_time":0.07261531971,"remaining_time":0.009902089051},
{"learn":[4.675027364],"iteration":88,"passed_time":0.0734597978,"remaining_time":0.009079300852},
{"learn":[4.662368584],"iteration":89,"passed_time":0.07435864023,"remaining_time":0.008262071136},
{"learn":[4.646206172],"iteration":90,"passed_time":0.07525677109,"remaining_time":0.00744297736},
{"learn":[4.641245848],"iteration":91,"passed_time":0.07612222606,"remaining_time":0.006619324005},
{"learn":[4.633900435],"iteration":92,"passed_time":0.07692239972,"remaining_time":0.005789858043},
{"learn":[4.624738236],"iteration":93,"passed_time":0.07769208272,"remaining_time":0.00495906911},
{"learn":[4.612798287],"iteration":94,"passed_time":0.07854216139,"remaining_time":0.004133797968},
{"learn":[4.605222001],"iteration":95,"passed_time":0.07931494264,"remaining_time":0.003304789276},
{"learn":[4.601725912],"iteration":96,"passed_time":0.08016112151,"remaining_time":0.002479209943},
{"learn":[4.59722371],"iteration":97,"passed_time":0.08103624727,"remaining_time":0.001653800965},
{"learn":[4.580235665],"iteration":98,"passed_time":0.0818836214,"remaining_time":0.0008271072869},
{"learn":[4.57591791],"iteration":99,"passed_time":0.08274856817,"remaining_time":0}
]}